mailroom/__init__.py
mailroom/email_client.py
mailroom/report_utils.py
tests/__init__.py
mailroom-0.0.1.dist-info/LICENSE
mailroom-0.0.1.dist-info/METADATA
mailroom-0.0.1.dist-info/WHEEL
mailroom-0.0.1.dist-info/top_level.txt
mailroom-0.0.1.dist-info/RECORD
