Metadata-Version: 2.1
Name: mailroom
Version: 0.0.1
Summary: Toolkit to generate & distribute html email reports
Home-page: https://github.com/MikeStrenk/mailroom
Author: Michael Strenk
License: UNKNOWN
Platform: UNKNOWN
Classifier: Development Status :: 3 - Alpha
Classifier: License :: OSI Approved :: MIT License
Classifier: Operating System :: OS Independent
Classifier: Programming Language :: Python :: 3.6
Requires-Dist: exchangelib
Requires-Dist: jinja2
